add_three_nevergonna/__init__.py
add_three_nevergonna/add_three.py
add_three_nevergonna-0.0.1.dist-info/METADATA
add_three_nevergonna-0.0.1.dist-info/WHEEL
add_three_nevergonna-0.0.1.dist-info/entry_points.txt
add_three_nevergonna-0.0.1.dist-info/license_files/LICENSE
add_three_nevergonna-0.0.1.dist-info/RECORD
