Metadata-Version: 2.1
Name: add-three-nevergonna
Version: 0.0.1
Summary: Adds three
Author-email: nevergonna <nevergonna@develomail.com>
